devolv_commit/__init__.py
devolv_commit/cli.py
devolv_commit/core.py
devolv_commit/utils.py
devolv_commit-0.1.1.dist-info/licenses/LICENSE
devolv_commit-0.1.1.dist-info/METADATA
devolv_commit-0.1.1.dist-info/WHEEL
devolv_commit-0.1.1.dist-info/entry_points.txt
devolv_commit-0.1.1.dist-info/top_level.txt
devolv_commit-0.1.1.dist-info/RECORD
