Metadata-Version: 2.4
Name: devolv-commit
Version: 0.1.1
Summary: Generate human-friendly Git commit messages from staged changes
Author-email: Devolvdev <devolv.dev@gmail.com>
License: MIT
Keywords: git,commit,automation,cli
Requires-Python: >=3.7
License-File: LICENSE
Dynamic: license-file
